burnman/__init__.py
burnman/calibrants/Anderson_1989.py
burnman/calibrants/Armentrout_2015.py
burnman/calibrants/Campbell_2009.py
burnman/calibrants/Chidester_2021.py
burnman/calibrants/Decker_1971.py
burnman/calibrants/Dewaele_2008.py
burnman/calibrants/Dewaele_2012.py
burnman/calibrants/Dewaele_2013.py
burnman/calibrants/Dewaele_2020.py
burnman/calibrants/Dorogokupets_2007.py
burnman/calibrants/Dorogokupets_2017.py
burnman/calibrants/Dubrovinsky_1998.py
burnman/calibrants/Fei_2007.py
burnman/calibrants/Fei_2016.py
burnman/calibrants/Holmes_1989.py
burnman/calibrants/Huang_2016.py
burnman/calibrants/LeGodec_2000.py
burnman/calibrants/Litasov_2013.py
burnman/calibrants/Matsui_2009.py
burnman/calibrants/Matsui_2010.py
burnman/calibrants/Matsui_2012.py
burnman/calibrants/Miozzi_2020.py
burnman/calibrants/Ono_2022.py
burnman/calibrants/Pigott_2015.py
burnman/calibrants/Shi_2022.py
burnman/calibrants/Shim_2002.py
burnman/calibrants/Sokolova_2013.py
burnman/calibrants/Speziale_2001.py
burnman/calibrants/Tange_2009.py
burnman/calibrants/Tateno_2019.py
burnman/calibrants/Tsuchiya_2003.py
burnman/calibrants/Walker_2002.py
burnman/calibrants/Zeng_2010.py
burnman/calibrants/Zha_2004.py
burnman/calibrants/Zha_2008.py
burnman/calibrants/Zhang_1999.py
burnman/calibrants/Zhao_1997.py
burnman/calibrants/Zhao_2000.py
burnman/calibrants/__init__.py
burnman/calibrants/tools.py
burnman/classes/__init__.py
burnman/classes/anisotropicmineral.py
burnman/classes/anisotropicsolution.py
burnman/classes/anisotropy.py
burnman/classes/averaging_schemes.py
burnman/classes/calibrant.py
burnman/classes/combinedmineral.py
burnman/classes/composite.py
burnman/classes/composition.py
burnman/classes/elasticsolution.py
burnman/classes/elasticsolutionmodel.py
burnman/classes/layer.py
burnman/classes/material.py
burnman/classes/mineral.py
burnman/classes/mineral_helpers.py
burnman/classes/perplex.py
burnman/classes/planet.py
burnman/classes/polytope.py
burnman/classes/seismic.py
burnman-2.1.0.dist-info/METADATA
burnman-2.1.0.dist-info/WHEEL
burnman-2.1.0.dist-info/RECORD
