Metadata-Version: 2.1
Name: burnman
Version: 2.1.0
Summary: A thermoelastic and thermodynamic toolkit for the Earth and planetary sciences
Home-page: https://geodynamics.github.io/burnman/
License: GPL
Author: The BurnMan Team
Author-email: bob.myhill@bristol.ac.uk
Requires-Python: >=3.8,<4.0
Classifier: License :: OSI Approved :: GNU General Public License v2 or later (GPLv2+)
Classifier: License :: Other/Proprietary License
Classifier: Operating System :: OS Independent
Classifier: Programming Language :: Python :: 3
Classifier: Programming Language :: Python :: 3.8
Classifier: Programming Language :: Python :: 3.9
Classifier: Programming Language :: Python :: 3.10
Classifier: Programming Language :: Python :: 3.11
Classifier: Programming Language :: Python :: 3.12
Classifier: Programming Language :: Python :: 3.13
Provides-Extra: dev
Requires-Dist: cvxpy (>=1.3,<2.0)
Requires-Dist: matplotlib (>=3.7,<4.0)
Requires-Dist: numba (>=0.59,<0.60)
Requires-Dist: numpy (>=1.24,<2.0)
Requires-Dist: pycddlib-standalone (>=3.0,<4.0) ; extra == "dev"
Requires-Dist: scipy (>=1.10,<2.0)
Requires-Dist: sympy (>=1.12,<2.0)
Project-URL: Documentation, https://burnman.readthedocs.io/
Project-URL: Repository, https://github.com/geodynamics/burnman
